pylint_comply/__init__.py
pylint_comply-0.1.0.dist-info/LICENSE
pylint_comply-0.1.0.dist-info/METADATA
pylint_comply-0.1.0.dist-info/WHEEL
pylint_comply-0.1.0.dist-info/RECORD
