Metadata-Version: 2.1
Name: pylint-comply
Version: 0.1.0
Summary: Pylint plugin to help automate code reviews and complying with quality standards.
Author: Svilen Piralkov
Author-email: svile@users.noreply.github.com
Requires-Python: >=3.11,<4.0
Classifier: Programming Language :: Python :: 3
Classifier: Programming Language :: Python :: 3.11
Classifier: Programming Language :: Python :: 3.12
